drf_triad_permissions/__init__.py
drf_triad_permissions/matching.py
drf_triad_permissions/permissions.py
drf_triad_permissions/policies.py
drf_triad_permissions/settings.py
drf_triad_permissions/templates/drf_triad_permissions/code.js.tpl
drf_triad_permissions/utils.py
drf_triad_permissions/views.py
drf_triad_permissions-0.2.0.dist-info/LICENSE
drf_triad_permissions-0.2.0.dist-info/WHEEL
drf_triad_permissions-0.2.0.dist-info/METADATA
drf_triad_permissions-0.2.0.dist-info/RECORD
