Metadata-Version: 2.1
Name: drf-triad-permissions
Version: 0.2.0
Summary: Django Rest Framework viewset permissions through triads
Home-page: https://github.com/lorinkoz/drf-triad-permissions
License: MIT
Keywords: django,djangorestframework,permissions
Author: Lorenzo Peña
Author-email: lorinkoz@gmail.com
Requires-Python: >=3.6,<4.0
Classifier: Development Status :: 3 - Alpha
Classifier: Framework :: Django
Classifier: Framework :: Django :: 2.0
Classifier: Framework :: Django :: 2.1
Classifier: Framework :: Django :: 2.2
Classifier: Framework :: Django :: 3.0
Classifier: License :: OSI Approved :: MIT License
Classifier: Programming Language :: Python :: 3
Classifier: Programming Language :: Python :: 3.6
Classifier: Programming Language :: Python :: 3.7
Classifier: Programming Language :: Python :: 3.8
Requires-Dist: django (>=2.0,<4.0)
Requires-Dist: djangorestframework (>=3.11.0,<4.0.0)
Project-URL: Repository, https://github.com/lorinkoz/drf-triad-permissions
